pearson/__init__.py
pearson/client.py
pearson/product.py
pearson_api-1.1.dist-info/LICENSE
pearson_api-1.1.dist-info/METADATA
pearson_api-1.1.dist-info/WHEEL
pearson_api-1.1.dist-info/top_level.txt
pearson_api-1.1.dist-info/RECORD
